SSVDpkg_663proj21/SSVDversion1.py
SSVDpkg_663proj21/SSVDversion2.py
SSVDpkg_663proj21/SSVDversion3.py
SSVDpkg_663proj21/SSVDversion4.py
SSVDpkg_663proj21/SSVDversion5.py
SSVDpkg_663proj21/__init__.py
SSVDpkg_663proj21/functions.py
SSVDpkg_663proj21-0.1.dist-info/LICENSE
SSVDpkg_663proj21-0.1.dist-info/METADATA
SSVDpkg_663proj21-0.1.dist-info/WHEEL
SSVDpkg_663proj21-0.1.dist-info/top_level.txt
SSVDpkg_663proj21-0.1.dist-info/RECORD
